rekt_googleplaces/__init__.py
rekt_googleplaces/client.py
rekt_googleplaces/errors.py
rekt_googleplaces/specs/googleplaces.yaml
rekt_googleplaces-0.2015.10.18.dist-info/DESCRIPTION.rst
rekt_googleplaces-0.2015.10.18.dist-info/METADATA
rekt_googleplaces-0.2015.10.18.dist-info/RECORD
rekt_googleplaces-0.2015.10.18.dist-info/WHEEL
rekt_googleplaces-0.2015.10.18.dist-info/metadata.json
rekt_googleplaces-0.2015.10.18.dist-info/top_level.txt
